setup.py
mldsnd_probability/Binomialdistribution.py
mldsnd_probability/Gaussiandistribution.py
mldsnd_probability/Generaldistribution.py
mldsnd_probability/__init__.py
mldsnd_probability.egg-info/PKG-INFO
mldsnd_probability.egg-info/SOURCES.txt
mldsnd_probability.egg-info/dependency_links.txt
mldsnd_probability.egg-info/not-zip-safe
mldsnd_probability.egg-info/top_level.txt