Metadata-Version: 1.0
Name: mldsnd-probability
Version: 0.1
Summary: Gaussian and Binomial Distributions
Home-page: UNKNOWN
Author: Juan Arroyo-Miranda
Author-email: something@nothing.com
License: UNKNOWN
Platform: UNKNOWN
